{
  "db_name": "SQLite",
  "query": "SELECT * FROM recording WHERE presentation_id = ?;",
  "describe": {
    "columns": [
      {
        "name": "id",
        "ordinal": 0,
        "type_info": "Integer"
      },
      {
        "name": "presentation_id",
        "ordinal": 1,
        "type_info": "Integer"
      },
      {
        "name": "name",
        "ordinal": 2,
        "type_info": "Text"
      },
      {
        "name": "vtt_path",
        "ordinal": 3,
        "type_info": "Text"
      },
      {
        "name": "captions_path",
        "ordinal": 4,
        "type_info": "Text"
      },
      {
        "name": "video_path",
        "ordinal": 5,
        "type_info": "Text"
      },
      {
        "name": "start",
        "ordinal": 6,
        "type_info": "Datetime"
      },
      {
        "name": "last_edited",
        "ordinal": 7,
        "type_info": "Datetime"
      }
    ],
    "parameters": {
      "Right": 1
    },
    "nullable": [
      false,
      false,
      false,
      false,
      false,
      false,
      false,
      true
    ]
  },
  "hash": "3cca223f636421dd60c502264282dc63ea9e07310194e774e4e1ea73f2e4665f"
}
